MANIFEST.in
setup.py
dist/wagtail-smart-selects-1.2.0.tar.gz
smart_selects/__init__.py
smart_selects/__init__.pyc
smart_selects/db_fields.py
smart_selects/db_fields.pyc
smart_selects/form_fields.py
smart_selects/form_fields.pyc
smart_selects/models.py
smart_selects/models.pyc
smart_selects/urls.py
smart_selects/urls.pyc
smart_selects/utils.py
smart_selects/utils.pyc
smart_selects/views.py
smart_selects/views.pyc
smart_selects/widgets.py
smart_selects/widgets.pyc
smart_selects/static/smart-selects/admin/js/chainedfk.js
smart_selects/static/smart-selects/admin/js/chainedm2m.js
wagtail_smart_selects.egg-info/PKG-INFO
wagtail_smart_selects.egg-info/SOURCES.txt
wagtail_smart_selects.egg-info/dependency_links.txt
wagtail_smart_selects.egg-info/top_level.txt