Metadata-Version: 1.0
Name: wagtail-smart-selects
Version: 1.2.0
Summary: Django application to handle chained model fields.
Home-page: UNKNOWN
Author: InfoPortugal S.A.
Author-email: UNKNOWN
License: UNKNOWN
Platform: UNKNOWN
